babel_transpiling/__init__.py
babel_transpiling/middlewares.py
babel_transpiling/storage.py
babel_transpiling/utils.py
babel_transpiling/static/npm/@babel/standalone@7.12.15/babel.min.js
babel_transpiling/static/npm/babel-plugin-transform-import-cssm@1.0.0/index.standalone.js
babel_transpiling/templatetags/__init__.py
babel_transpiling/templatetags/babel_transpiling.py
django_babel_transpiling-0.3.2.dist-info/METADATA
django_babel_transpiling-0.3.2.dist-info/RECORD
django_babel_transpiling-0.3.2.dist-info/WHEEL
django_babel_transpiling-0.3.2.dist-info/top_level.txt
