Metadata-Version: 2.1
Name: django-babel-transpiling
Version: 0.3.2
Summary: Bring babel to your django project, transpiling static .jsx files on the fly, without NodeJS require!
Home-page: https://github.com/DistPub/django-babel-transpiling
Author: Smite Chow
Author-email: xiaopengyou2no1@gmail.com
License: MIT
Platform: UNKNOWN
Classifier: Development Status :: 5 - Production/Stable
Classifier: Environment :: Console
Classifier: Framework :: Django
Classifier: Intended Audience :: Developers
Classifier: License :: OSI Approved :: MIT License
Classifier: Natural Language :: English
Classifier: Operating System :: OS Independent
Classifier: Programming Language :: Python
Classifier: Programming Language :: Python :: 3
Classifier: Programming Language :: Python :: 3.6
Classifier: Programming Language :: Python :: 3 :: Only
Classifier: Topic :: Internet :: WWW/HTTP
Requires-Python: >=3.6
Requires-Dist: whitenoise
Requires-Dist: py-mini-racer
